LICENSE
MANIFEST.in
README
setup.py
bin/ircstat
ircstat/__init__.py
ircstat/config.py
ircstat/core.py
ircstat/defaults.py
ircstat/ent.py
ircstat/graphs.py
ircstat/lib.py
ircstat/log.py
ircstat/parser.py
ircstat.egg-info/PKG-INFO
ircstat.egg-info/SOURCES.txt
ircstat.egg-info/dependency_links.txt
ircstat.egg-info/requires.txt
ircstat.egg-info/top_level.txt
ircstat/plugins/__init__.py
ircstat/plugins/base.py
ircstat/plugins/highbrow.py
ircstat/plugins/totals.py