Metadata-Version: 1.1
Name: ircstat
Version: 0.1.1
Summary: generate statistics and graphs from IRC channel logs
Home-page: https://github.com/jreese/ircstat
Author: John Reese
Author-email: john@noswap.com
License: MIT License
Platform: UNKNOWN
Classifier: License :: OSI Approved :: MIT License
Classifier: Operating System :: OS Independent
Classifier: Programming Language :: Python
Classifier: Programming Language :: Python :: 3
Classifier: Programming Language :: Python :: 3.2
Classifier: Programming Language :: Python :: 3.3
Classifier: Topic :: Utilities
Classifier: Development Status :: 2 - Pre-Alpha
Requires: matplotlib (>=1.3.0)
Requires: Jinja2 (>=2.6)
